{
  "uid" : "254b2ded7c63fd4a",
  "name" : "TestExpertGuid.test_all_label",
  "title" : "Test all label",
  "time" : {
    "start" : 1519961302389,
    "stop" : 1519961302594,
    "duration" : 205
  },
  "summary" : {
    "attachments" : 0,
    "steps" : 1
  },
  "failure" : null,
  "description" : {
    "value" : "专家频道5大分类",
    "type" : "TEXT"
  },
  "severity" : "NORMAL",
  "status" : "PASSED",
  "testId" : null,
  "suite" : {
    "uid" : "a606d51bbd1226e8",
    "name" : "testscripts.test_expert",
    "title" : "Test expert"
  },
  "steps" : [ {
    "name" : "获取专家引导5大分类",
    "title" : "获取专家引导5大分类",
    "time" : {
      "start" : 1519961302394,
      "stop" : 1519961302594,
      "duration" : 200
    },
    "summary" : {
      "attachments" : 0,
      "steps" : 0
    },
    "status" : "PASSED",
    "attachments" : [ ],
    "steps" : [ ]
  } ],
  "attachments" : [ ],
  "issues" : [ ],
  "labels" : [ {
    "name" : "host",
    "value" : "fireln"
  }, {
    "name" : "framework",
    "value" : "pytest"
  }, {
    "name" : "suite-name",
    "value" : "testscripts.test_expert"
  }, {
    "name" : "suite-title",
    "value" : null
  }, {
    "name" : "severity",
    "value" : "normal"
  }, {
    "name" : "language",
    "value" : "cpython3"
  }, {
    "name" : "thread",
    "value" : "13784-MainThread"
  } ],
  "parameters" : [ ]
}