{
  "uid" : "8e2a2b52f00b185d",
  "name" : "TestExpert.TestExpertGuid.test_create_label",
  "title" : "Test create label",
  "time" : {
    "start" : 1519968190501,
    "stop" : 1519968190559,
    "duration" : 58
  },
  "summary" : {
    "attachments" : 0,
    "steps" : 1
  },
  "failure" : null,
  "description" : {
    "value" : "自定义分类,然后删除",
    "type" : "TEXT"
  },
  "severity" : "NORMAL",
  "status" : "PASSED",
  "testId" : null,
  "suite" : {
    "uid" : "ac9c4d2e5163cca6",
    "name" : "testscripts.test_expert",
    "title" : "Test expert"
  },
  "steps" : [ {
    "name" : "自定义分类",
    "title" : "自定义分类",
    "time" : {
      "start" : 1519968190504,
      "stop" : 1519968190559,
      "duration" : 55
    },
    "summary" : {
      "attachments" : 0,
      "steps" : 0
    },
    "status" : "PASSED",
    "attachments" : [ ],
    "steps" : [ ]
  } ],
  "attachments" : [ ],
  "issues" : [ ],
  "labels" : [ {
    "name" : "host",
    "value" : "fireln"
  }, {
    "name" : "feature",
    "value" : "专家频道"
  }, {
    "name" : "framework",
    "value" : "pytest"
  }, {
    "name" : "suite-name",
    "value" : "testscripts.test_expert"
  }, {
    "name" : "thread",
    "value" : "22484-MainThread"
  }, {
    "name" : "suite-title",
    "value" : null
  }, {
    "name" : "story",
    "value" : "专家引导"
  }, {
    "name" : "severity",
    "value" : "normal"
  }, {
    "name" : "language",
    "value" : "cpython3"
  } ],
  "parameters" : [ ]
}